{"singlePage": [], "startSite": "", "filingNum": "", "onePageListNum": 15, "commentLabelColor": "#006b75", "yearColorList": ["#bc4c00", "#0969da", "#1f883d", "#A333D0"], "i18n": "CN", "themeMode": "manual", "dayTheme": "light", "nightTheme": "dark", "urlMode": "pinyin", "script": "", "style": "", "head": "", "indexScript": "", "indexStyle": "", "bottomText": "", "showPostSource": 1, "iconList": {}, "UTC": 8, "rssSplit": "sentence", "exlink": {}, "needComment": 1, "allHead": "", "title": "\u590f\u306eblog", "subTitle": "\u5206\u4eab\u7f8e\u56fe", "avatarUrl": "https://avatars.githubusercontent.com/u/195541301?v=4", "GMEEK_VERSION": "last", "postListJson": {"P1": {"htmlDir": "docs/post/test.html", "labels": ["test"], "postTitle": "test", "postUrl": "post/test.html", "postSourceUrl": "https://github.com/yss161/yss161.github.io/issues/1", "commentNum": 0, "description": "", "wordCount": 0, "top": 0, "createdAt": 1767943804, "style": "", "script": "", "head": "", "ogImage": "https://avatars.githubusercontent.com/u/195541301?v=4", "createdDate": "2026-01-09", "dateLabelColor": "#1f883d"}, "P2": {"htmlDir": "docs/post/\ud83d\ude0b.html", "labels": ["photo"], "postTitle": "\ud83d\ude0b", "postUrl": "post/%F0%9F%98%8B.html", "postSourceUrl": "https://github.com/yss161/yss161.github.io/issues/2", "commentNum": 0, "wordCount": 89, "description": "![Image](https://github.com/user-attachments/assets/1eb916b5-8867-418b-b441-85d4f68ec807)\u3002", "top": 0, "createdAt": 1767944521, "style": "", "script": "", "head": "", "ogImage": "https://avatars.githubusercontent.com/u/195541301?v=4", "createdDate": "2026-01-09", "dateLabelColor": "#1f883d"}, "P3": {"htmlDir": "docs/post/mo-jian---zhi-geng-niao.html", "labels": ["photo"], "postTitle": "\u58a8\u89c1-\u77e5\u66f4\u9e1f", "postUrl": "post/mo-jian---zhi-geng-niao.html", "postSourceUrl": "https://github.com/yss161/yss161.github.io/issues/3", "commentNum": 1, "wordCount": 269, "description": "![Image](https://github.com/user-attachments/assets/1eb5d6f2-6041-4e3e-b4a8-ef1c5dc99914)\n![Image](https://github.com/user-attachments/assets/1dc345e4-e11b-4bb7-8006-daee06b167d9)\n![Image](https://github.com/user-attachments/assets/ac360cd8-6afc-4ec8-918c-b1b3bc44697b)\u3002", "top": 0, "createdAt": 1767944769, "style": "", "script": "", "head": "", "ogImage": "https://avatars.githubusercontent.com/u/195541301?v=4", "createdDate": "2026-01-09", "dateLabelColor": "#1f883d"}, "P8": {"htmlDir": "docs/post/bie-chao-chao---pei-li-qia.html", "labels": ["video"], "postTitle": "\u522b\u5435\u5435-\u4f69\u4e3d\u5361", "postUrl": "post/bie-chao-chao---pei-li-qia.html", "postSourceUrl": "https://github.com/yss161/yss161.github.io/issues/8", "commentNum": 0, "wordCount": 79, "description": "https://github.com/user-attachments/assets/defa3fce-94c7-4901-9b08-59a56f37b3d8\u3002", "top": 0, "createdAt": 1767947531, "style": "", "script": "", "head": "", "ogImage": "https://avatars.githubusercontent.com/u/195541301?v=4", "createdDate": "2026-01-09", "dateLabelColor": "#1f883d"}, "P12": {"htmlDir": "docs/post/\ud83d\udc46\ud83e\udd13.html", "labels": ["photo"], "postTitle": "\ud83d\udc46\ud83e\udd13", "postUrl": "post/%F0%9F%91%86%F0%9F%A4%93.html", "postSourceUrl": "https://github.com/yss161/yss161.github.io/issues/12", "commentNum": 0, "wordCount": 89, "description": "![Image](https://github.com/user-attachments/assets/eb9c6d3c-4f42-443f-83d0-5fe5a6fa67b4)\u3002", "top": 0, "createdAt": 1767956023, "style": "", "script": "", "head": "", "ogImage": "https://avatars.githubusercontent.com/u/195541301?v=4", "createdDate": "2026-01-09", "dateLabelColor": "#1f883d"}, "P13": {"htmlDir": "docs/post/bi-chen---qing-yi.html", "labels": ["photo"], "postTitle": "\u5f7c\u6668-\u9752\u8863", "postUrl": "post/bi-chen---qing-yi.html", "postSourceUrl": "https://github.com/yss161/yss161.github.io/issues/13", "commentNum": 0, "wordCount": 2433, "description": "<img width='1452' height='3024' alt='Image' src='https://github.com/user-attachments/assets/db32305b-9b25-4c4c-9494-28887cfe138a' />\n<img width='1101' height='774' alt='Image' src='https://github.com/user-attachments/assets/a4a2d762-6dc8-4ae5-88da-6d0c0bc3a847' />\n<img width='1080' height='1440' alt='Image' src='https://github.com/user-attachments/assets/0f36fece-ddda-4ed6-a597-885aba3c8939' />\n<img width='1500' height='2000' alt='Image' src='https://github.com/user-attachments/assets/81873baa-a0d0-4fb0-bc52-5f06927adb07' />\n<img width='1500' height='2000' alt='Image' src='https://github.com/user-attachments/assets/168d4d76-0c7e-44a2-91a6-6ea71ea9e629' />\n<img width='1500' height='2000' alt='Image' src='https://github.com/user-attachments/assets/981126f0-95ee-40d1-8232-09138b02320d' />\n<img width='1500' height='2000' alt='Image' src='https://github.com/user-attachments/assets/08af380f-5dab-48fd-8fac-1e7528f4f403' />\n<img width='1500' height='2000' alt='Image' src='https://github.com/user-attachments/assets/67078608-1cc0-480a-b9ae-07528655363b' />\n<img width='1500' height='2000' alt='Image' src='https://github.com/user-attachments/assets/791d9a38-5096-4056-9b1d-20876d68e7a2' />\n<img width='1500' height='2250' alt='Image' src='https://github.com/user-attachments/assets/3a8bf661-b09c-4f25-9efc-848fc0d31014' />\n<img width='1500' height='2250' alt='Image' src='https://github.com/user-attachments/assets/6b9a623b-eb03-480b-abd9-d234a34d1991' />\n<img width='1500' height='2000' alt='Image' src='https://github.com/user-attachments/assets/790b73a3-5dce-4b4b-b4b3-933e9741669e' />\n<img width='1500' height='2000' alt='Image' src='https://github.com/user-attachments/assets/d3d89c47-5500-4785-96ba-41474fc74159' />\n<img width='1500' height='2866' alt='Image' src='https://github.com/user-attachments/assets/3f5e5027-f4f7-4a5e-a12a-89476d6029cd' />\n<img width='1500' height='2866' alt='Image' src='https://github.com/user-attachments/assets/c5c80aa4-bf5b-408e-bf83-b7c8e3e6c2bb' />\n<!-- Failed to upload 'IMG_9379.PNG' -->\n<img width='1500' height='2222' alt='Image' src='https://github.com/user-attachments/assets/86120161-b9d4-436b-952c-9c4e6bca8446' />\n<img width='1500' height='2000' alt='Image' src='https://github.com/user-attachments/assets/1000eadf-aa3f-4314-bcc7-573bfcd73204' />\n<img width='1500' height='2000' alt='Image' src='https://github.com/user-attachments/assets/d26a4031-6d3f-44ed-9770-b6357fd9e060' />\u3002", "top": 0, "createdAt": 1767956282, "style": "", "script": "", "head": "", "ogImage": "https://avatars.githubusercontent.com/u/195541301?v=4", "createdDate": "2026-01-09", "dateLabelColor": "#1f883d"}, "P14": {"htmlDir": "docs/post/bi-chen---zhao.html", "labels": ["photo"], "postTitle": "\u5f7c\u6668-\u7167", "postUrl": "post/bi-chen---zhao.html", "postSourceUrl": "https://github.com/yss161/yss161.github.io/issues/14", "commentNum": 0, "wordCount": 2249, "description": "<img width='4096' height='3072' alt='Image' src='https://github.com/user-attachments/assets/c3e506cc-974d-431e-8056-3884773353f0' />\n<img width='1500' height='2000' alt='Image' src='https://github.com/user-attachments/assets/f6d06ffa-2931-4ad0-9801-3a76d2e37d3f' />\n<img width='1920' height='1080' alt='Image' src='https://github.com/user-attachments/assets/f07915dc-ba6c-4abb-a61c-dc7a19eac01b' />\n<img width='1500' height='2250' alt='Image' src='https://github.com/user-attachments/assets/f3836348-4b7d-406c-be46-881fc195fadf' />\n<!-- Failed to upload 'IMG_9326.PNG' -->\n<!-- Failed to upload 'IMG_9325.PNG' -->\n<img width='2881' height='4320' alt='Image' src='https://github.com/user-attachments/assets/7ce4f89b-2da2-449a-89f5-db61d57b4e9d' />\n<img width='1500' height='2000' alt='Image' src='https://github.com/user-attachments/assets/a08bf4a9-46b5-480f-9d9e-b15a8c7c8f30' />\n<img width='1500' height='2000' alt='Image' src='https://github.com/user-attachments/assets/58b5482f-261f-4e66-a723-20d60f73c981' />\n<img width='1500' height='2000' alt='Image' src='https://github.com/user-attachments/assets/de4468e8-d6b7-4f9e-8ff0-e503ca344ddb' />\n<img width='3024' height='4032' alt='Image' src='https://github.com/user-attachments/assets/660fb07d-be90-4564-9409-c5911bf6a981' />\n<!-- Failed to upload 'IMG_9318.PNG' -->\n<img width='1320' height='988' alt='Image' src='https://github.com/user-attachments/assets/bbff10c4-fc31-4696-8b35-f78e447a5e03' />\n<img width='1500' height='2000' alt='Image' src='https://github.com/user-attachments/assets/0afca6f7-6988-4788-bbd9-c4eced2372cb' />\n<img width='1500' height='2000' alt='Image' src='https://github.com/user-attachments/assets/ee48c366-44d5-44f9-a2ae-4f4a367e6597' />\n<img width='1500' height='2000' alt='Image' src='https://github.com/user-attachments/assets/976d23b9-9918-4d16-b201-b2669314eb85' />\n<img width='2000' height='1500' alt='Image' src='https://github.com/user-attachments/assets/ad0a365c-d0dc-4418-b706-fd95b5990bfb' />\n<img width='2000' height='1500' alt='Image' src='https://github.com/user-attachments/assets/8862de33-12c4-4ccb-8d83-6e36cebf7e84' />\n<img width='2000' height='1500' alt='Image' src='https://github.com/user-attachments/assets/efa02de4-1ee8-4ae8-bf7f-d8e1be30a087' />\u3002", "top": 0, "createdAt": 1767956461, "style": "", "script": "", "head": "", "ogImage": "https://avatars.githubusercontent.com/u/195541301?v=4", "createdDate": "2026-01-09", "dateLabelColor": "#1f883d"}}, "singeListJson": {}, "labelColorDict": {"documentation": "#0075ca", "photo": "#c721a1", "test": "#a4af2c", "video": "#37727b"}, "displayTitle": "\u590f\u306eblog", "faviconUrl": "https://avatars.githubusercontent.com/u/195541301?v=4", "ogImage": "https://avatars.githubusercontent.com/u/195541301?v=4", "primerCSS": "<link href='https://mirrors.sustech.edu.cn/cdnjs/ajax/libs/Primer/21.0.7/primer.css' rel='stylesheet' />", "homeUrl": "https://yss161.github.io", "prevUrl": "disabled", "nextUrl": "disabled"}